odoo/addons/ssi_stock_fixed_asset/README.rst
odoo/addons/ssi_stock_fixed_asset/__init__.py
odoo/addons/ssi_stock_fixed_asset/__manifest__.py
odoo/addons/ssi_stock_fixed_asset/models/__init__.py
odoo/addons/ssi_stock_fixed_asset/models/account_move_line.py
odoo/addons/ssi_stock_fixed_asset/models/fixed_asset_asset.py
odoo/addons/ssi_stock_fixed_asset/models/product_product.py
odoo/addons/ssi_stock_fixed_asset/models/stock_production_lot.py
odoo/addons/ssi_stock_fixed_asset/static/description/icon.png
odoo/addons/ssi_stock_fixed_asset/views/fixed_asset_asset_views.xml
odoo/addons/ssi_stock_fixed_asset/views/product_product_views.xml
odoo/addons/ssi_stock_fixed_asset/views/stock_production_lot_views.xml
odoo14_addon_ssi_stock_fixed_asset-14.0.2.2.0.dist-info/METADATA
odoo14_addon_ssi_stock_fixed_asset-14.0.2.2.0.dist-info/WHEEL
odoo14_addon_ssi_stock_fixed_asset-14.0.2.2.0.dist-info/top_level.txt
odoo14_addon_ssi_stock_fixed_asset-14.0.2.2.0.dist-info/RECORD
